Metadata-Version: 2.1
Name: sparticleinc-skywalking
Version: 1.0.4
Summary: The Python Agent for Apache SkyWalking, which provides the native tracing/metrics/logging/profiling abilities for Python projects.
Home-page: https://skywalking.apache.org/
License: Apache-2.0
Keywords: skywalking,tracing,metrics,logging,profiling,observability,distributed-tracing,apm,python
Author: Apache Software Foundation
Author-email: dev@skywalking.apache.org
Maintainer: Apache SkyWalking Community
Maintainer-email: dev@skywalking.apache.org
Requires-Python: >=3.7,<3.12
Classifier: License :: OSI Approved :: Apache Software License
Classifier: Operating System :: OS Independent
Classifier: Programming Language :: Python
Classifier: Programming Language :: Python :: 3
Classifier: Programming Language :: Python :: 3.7
Classifier: Programming Language :: Python :: 3.8
Classifier: Programming Language :: Python :: 3.9
Classifier: Programming Language :: Python :: 3.10
Classifier: Programming Language :: Python :: 3.11
Classifier: Programming Language :: Python :: 3
Classifier: Programming Language :: Python :: 3.10
Classifier: Programming Language :: Python :: 3.11
Classifier: Programming Language :: Python :: 3.7
Classifier: Programming Language :: Python :: 3.8
Classifier: Programming Language :: Python :: 3.9
Classifier: Topic :: Software Development
Classifier: Topic :: System :: Monitoring
Provides-Extra: all
Provides-Extra: http
Provides-Extra: kafka
Requires-Dist: grpcio
Requires-Dist: grpcio-tools
Requires-Dist: kafka-python ; extra == "all" or extra == "kafka"
Requires-Dist: packaging
Requires-Dist: psutil
Requires-Dist: requests (>=2.26.0) ; extra == "all" or extra == "http"
Requires-Dist: wrapt
Project-URL: Bug Tracker, https://github.com/apache/skywalking/issues
Project-URL: Documentation, https://github.com/sparticleinc/skywalking-python/next/readme/
Project-URL: Repository, https://github.com/sparticleinc/skywalking-python
